[{"text": "Remote", "name": "Remote", "id": 0, "children": [{"text": "button", "name": "button", "id": 1, "objs": ["original-30", "original-13", "original-14"]}, {"text": "button", "name": "button", "id": 2, "objs": ["original-29", "original-11", "original-12"]}, {"text": "button", "name": "button", "id": 3, "objs": ["original-28", "original-15", "original-16"]}, {"text": "button", "name": "button", "id": 4, "objs": ["original-19", "original-20"]}, {"text": "button", "name": "button", "id": 5, "objs": ["original-27", "original-9", "original-10"]}, {"text": "button", "name": "button", "id": 6, "objs": ["original-17", "original-18"]}, {"text": "button", "name": "button", "id": 7, "objs": ["original-21", "original-22"]}, {"text": "button", "name": "button", "id": 8, "objs": ["original-7", "original-8"]}, {"text": "button", "name": "button", "id": 9, "objs": ["original-5", "original-6"]}, {"text": "button", "name": "button", "id": 10, "objs": ["original-23", "original-24"]}, {"text": "button", "name": "button", "id": 11, "objs": ["original-25"]}, {"text": "button", "name": "button", "id": 12, "objs": ["original-31", "original-2"]}, {"text": "base_body", "name": "base_body", "id": 13, "objs": ["original-26", "original-4", "original-3", "original-32", "original-1"]}]}]